maxsetup.py
maxsetup-0.8.0.dist-info/entry_points.txt
maxsetup-0.8.0.dist-info/LICENSE
maxsetup-0.8.0.dist-info/WHEEL
maxsetup-0.8.0.dist-info/METADATA
maxsetup-0.8.0.dist-info/RECORD
