Metadata-Version: 2.1
Name: maxsetup
Version: 0.8.0
Summary: This is a module that automates the file structure and settings of a new project.
Author: Max Ludden
Author-email: dev@maxludden.com
Requires-Python: >=3.10,<4.0
Classifier: Programming Language :: Python :: 3
Classifier: Programming Language :: Python :: 3.10
Classifier: Programming Language :: Python :: 3.11
Requires-Dist: loguru (>=0.6.0,<0.7.0)
Requires-Dist: max-yaml (>=0.1.0,<0.2.0)
Requires-Dist: maxcolor (>=1.0.0,<2.0.0)
Requires-Dist: maxconsole (>=0.4.0,<0.5.0)
Requires-Dist: maxprogress (>=0.4.0,<0.5.0)
Requires-Dist: rich (>=12.6.0,<13.0.0)
Requires-Dist: ujson (>=5.5.0,<6.0.0)
